{
	"partitions" : [
		{
			"name" : "Top",
			"pins" : [
				{
					"name" : "FPGA_TX",
					"strict" : false
				},
				{
					"name" : "DAC1[0]",
					"strict" : false
				},
				{
					"name" : "DAC1[1]",
					"strict" : false
				},
				{
					"name" : "DAC1[2]",
					"strict" : false
				},
				{
					"name" : "DAC1[3]",
					"strict" : false
				},
				{
					"name" : "DAC1[4]",
					"strict" : false
				},
				{
					"name" : "DAC1[5]",
					"strict" : false
				},
				{
					"name" : "DAC1[6]",
					"strict" : false
				},
				{
					"name" : "DAC1[7]",
					"strict" : false
				},
				{
					"name" : "DAC1[8]",
					"strict" : false
				},
				{
					"name" : "DAC1[9]",
					"strict" : false
				},
				{
					"name" : "DAC1[10]",
					"strict" : false
				},
				{
					"name" : "DAC1[11]",
					"strict" : false
				},
				{
					"name" : "DAC1[12]",
					"strict" : false
				},
				{
					"name" : "DAC1[13]",
					"strict" : false
				},
				{
					"name" : "DAC1[14]",
					"strict" : false
				},
				{
					"name" : "DAC1[15]",
					"strict" : false
				},
				{
					"name" : "DAC_RST",
					"strict" : false
				},
				{
					"name" : "MOSI",
					"strict" : false
				},
				{
					"name" : "SCLK",
					"strict" : false
				},
				{
					"name" : "CS_ADC",
					"strict" : false
				},
				{
					"name" : "CS_DAC",
					"strict" : false
				},
				{
					"name" : "SCL",
					"strict" : false
				},
				{
					"name" : "SDRAM_ADDR[0]",
					"strict" : false
				},
				{
					"name" : "SDRAM_ADDR[1]",
					"strict" : false
				},
				{
					"name" : "SDRAM_ADDR[2]",
					"strict" : false
				},
				{
					"name" : "SDRAM_ADDR[3]",
					"strict" : false
				},
				{
					"name" : "SDRAM_ADDR[4]",
					"strict" : false
				},
				{
					"name" : "SDRAM_ADDR[5]",
					"strict" : false
				},
				{
					"name" : "SDRAM_ADDR[6]",
					"strict" : false
				},
				{
					"name" : "SDRAM_ADDR[7]",
					"strict" : false
				},
				{
					"name" : "SDRAM_ADDR[8]",
					"strict" : false
				},
				{
					"name" : "SDRAM_ADDR[9]",
					"strict" : false
				},
				{
					"name" : "SDRAM_ADDR[10]",
					"strict" : false
				},
				{
					"name" : "SDRAM_ADDR[11]",
					"strict" : false
				},
				{
					"name" : "SDRAM_BA[0]",
					"strict" : false
				},
				{
					"name" : "SDRAM_BA[1]",
					"strict" : false
				},
				{
					"name" : "SDRAM_CAS_N",
					"strict" : false
				},
				{
					"name" : "SDRAM_CS_N",
					"strict" : false
				},
				{
					"name" : "SDRAM_DQM[0]",
					"strict" : false
				},
				{
					"name" : "SDRAM_DQM[1]",
					"strict" : false
				},
				{
					"name" : "SDRAM_RAS_N",
					"strict" : false
				},
				{
					"name" : "SDRAM_WE_N",
					"strict" : false
				},
				{
					"name" : "EPCS_ASDO",
					"strict" : false
				},
				{
					"name" : "EPCS_DCLK",
					"strict" : false
				},
				{
					"name" : "EPCS_NCSO",
					"strict" : false
				},
				{
					"name" : "SDA",
					"strict" : false
				},
				{
					"name" : "SDRAM_DQ[0]",
					"strict" : false
				},
				{
					"name" : "SDRAM_DQ[1]",
					"strict" : false
				},
				{
					"name" : "SDRAM_DQ[2]",
					"strict" : false
				},
				{
					"name" : "SDRAM_DQ[3]",
					"strict" : false
				},
				{
					"name" : "SDRAM_DQ[4]",
					"strict" : false
				},
				{
					"name" : "SDRAM_DQ[5]",
					"strict" : false
				},
				{
					"name" : "SDRAM_DQ[6]",
					"strict" : false
				},
				{
					"name" : "SDRAM_DQ[7]",
					"strict" : false
				},
				{
					"name" : "SDRAM_DQ[8]",
					"strict" : false
				},
				{
					"name" : "SDRAM_DQ[9]",
					"strict" : false
				},
				{
					"name" : "SDRAM_DQ[10]",
					"strict" : false
				},
				{
					"name" : "SDRAM_DQ[11]",
					"strict" : false
				},
				{
					"name" : "SDRAM_DQ[12]",
					"strict" : false
				},
				{
					"name" : "SDRAM_DQ[13]",
					"strict" : false
				},
				{
					"name" : "SDRAM_DQ[14]",
					"strict" : false
				},
				{
					"name" : "SDRAM_DQ[15]",
					"strict" : false
				},
				{
					"name" : "SYNC_IN",
					"strict" : false
				},
				{
					"name" : "EPCS_DATA0",
					"strict" : false
				},
				{
					"name" : "ADC_D1[13]",
					"strict" : false
				},
				{
					"name" : "ADC_D1[12]",
					"strict" : false
				},
				{
					"name" : "ADC_D1[11]",
					"strict" : false
				},
				{
					"name" : "ADC_D1[10]",
					"strict" : false
				},
				{
					"name" : "ADC_D1[9]",
					"strict" : false
				},
				{
					"name" : "ADC_D1[8]",
					"strict" : false
				},
				{
					"name" : "ADC_D1[7]",
					"strict" : false
				},
				{
					"name" : "ADC_D1[6]",
					"strict" : false
				},
				{
					"name" : "ADC_D1[5]",
					"strict" : false
				},
				{
					"name" : "ADC_D1[4]",
					"strict" : false
				},
				{
					"name" : "ADC_D1[3]",
					"strict" : false
				},
				{
					"name" : "ADC_D1[2]",
					"strict" : false
				},
				{
					"name" : "ADC_D1[1]",
					"strict" : false
				},
				{
					"name" : "ADC_D1[0]",
					"strict" : false
				},
				{
					"name" : "MISO",
					"strict" : false
				},
				{
					"name" : "FPGA_RX",
					"strict" : false
				},
				{
					"name" : "altera_reserved_tms",
					"strict" : false
				},
				{
					"name" : "altera_reserved_tck",
					"strict" : false
				},
				{
					"name" : "altera_reserved_tdi",
					"strict" : false
				},
				{
					"name" : "altera_reserved_tdo",
					"strict" : false
				}
			]
		}
	]
}